<?xml version="1.0" encoding="UTF-8"?>
<comment version="3.0">
  <caption>Team of crisis managers solving businessman problems</caption>
  <note>Team of crisis managers solving businessman problems. Employees with lightbulb unraveling tangle. Vector illustration for teamwork, solution, management concept</note>
  <place/>
  <categories>
    <category value="leadership"/>
    <category value="challenge"/>
    <category value="management"/>
    <category value="symbol"/>
    <category value="technology"/>
    <category value="web"/>
    <category value="tangle"/>
    <category value="tangled"/>
    <category value="rope"/>
    <category value="unraveling"/>
    <category value="problem"/>
    <category value="solving"/>
    <category value="concept"/>
    <category value="manager"/>
    <category value="professional"/>
    <category value="help"/>
    <category value="lightbulb"/>
    <category value="bulb"/>
    <category value="shining"/>
    <category value="idea"/>
    <category value="crisis"/>
    <category value="trouble"/>
    <category value="cartoon"/>
    <category value="business"/>
    <category value="work"/>
    <category value="solution"/>
    <category value="vector"/>
    <category value="people"/>
    <category value="achievement"/>
    <category value="abstract"/>
    <category value="hand"/>
    <category value="metaphor"/>
    <category value="progress"/>
    <category value="teamwork"/>
    <category value="character"/>
    <category value="conceptual"/>
    <category value="design"/>
    <category value="idea"/>
    <category value="illustration"/>
    <category value="strategy"/>
    <category value="team"/>
    <category value="background"/>
    <category value="banner"/>
    <category value="growth"/>
  </categories>
</comment>
